Metadata-Version: 1.2
Name: takoshell
Version: 0.2.8
Summary: Pythonic shell language and command prompt
Home-page: https://takoshell.org
Author: Adam Hartz
Author-email: hartz@mit.edu
Maintainer: Adam Hartz
License: GPLv3+
Platform: Cross Platform
Classifier: Development Status :: 4 - Beta
Classifier: Environment :: Console
Classifier: Intended Audience :: Developers
Classifier: Intended Audience :: End Users/Desktop
Classifier: Natural Language :: English
Classifier: Operating System :: POSIX
Classifier: Programming Language :: Python :: 3 :: Only
Classifier: Topic :: System :: Shells
Classifier: License :: OSI Approved :: GNU General Public License v3 or later (GPLv3+)
